README.md
setup.py
flask_jwtlogin/JWTLogin.py
flask_jwtlogin/__init__.py
flask_jwtlogin/errors.py
flask_jwtlogin/users.py
flask_jwtlogin.egg-info/PKG-INFO
flask_jwtlogin.egg-info/SOURCES.txt
flask_jwtlogin.egg-info/dependency_links.txt
flask_jwtlogin.egg-info/not-zip-safe
flask_jwtlogin.egg-info/requires.txt
flask_jwtlogin.egg-info/top_level.txt
test/test_app.py