Metadata-Version: 2.1
Name: flask_jwtlogin
Version: 0.2.1
Summary: flask extension to handle login users in APIs
Home-page: https://github.com/AlexPraefectus/flask-jwtlogin
Author: Alex Korienev
Author-email: alexkorienev@gmail.com
License: BSD
Download-URL: https://github.com/AlexPraefectus/flask-jwtlogin/archive/0.1.tar.gz
Platform: UNKNOWN
